iMATURE_cardio/MatplotlibWidget5.py
iMATURE_cardio/Qt5file.py
iMATURE_cardio/Resource_rc5.py
iMATURE_cardio/__init__.py
iMATURE_cardio/__main__.py
iMATURE_cardio/command_line.py
iMATURE_cardio/iMATURE.py
iMATURE_cardio/iMATURE_highres2.png
iMATURE_cardio/iMATURE_icon.ico
iMATURE_cardio/models/Human iPSC-CM (Kernik et al-2019).mmt
iMATURE_cardio-1.1.2.3.dist-info/DESCRIPTION.rst
iMATURE_cardio-1.1.2.3.dist-info/METADATA
iMATURE_cardio-1.1.2.3.dist-info/RECORD
iMATURE_cardio-1.1.2.3.dist-info/WHEEL
iMATURE_cardio-1.1.2.3.dist-info/entry_points.txt
iMATURE_cardio-1.1.2.3.dist-info/metadata.json
iMATURE_cardio-1.1.2.3.dist-info/top_level.txt
