Metadata-Version: 2.0
Name: iMATURE-cardio
Version: 1.1.2.3
Summary: iMATURE_cardio
Home-page: http://www.jordiheijman.net/
Author: UNKNOWN
Author-email: UNKNOWN
License: UNKNOWN
Platform: UNKNOWN
Requires-Dist: myokit
